panel_components/__init__.py
panel_components/component.py
panel_components/file.py
panel_components/mpl.py
panel_components/tags.py
panel_components/utils.py
panel_components/vue.py
panel_components/www/ace/ace.js
panel_components/www/ace/ext-language_tools.js
panel_components/www/bokeh/bokeh-gl.min.js
panel_components/www/bokeh/bokeh-tables.min.js
panel_components/www/bokeh/bokeh-widgets.min.js
panel_components/www/bokeh/bokeh.min.js
panel_components/www/bokeh/panel.css
panel_components/www/bokeh/panel.min.js
panel_components/www/katex/auto-render.min.js
panel_components/www/katex/fonts/KaTeX_AMS-Regular.woff
panel_components/www/katex/fonts/KaTeX_Caligraphic-Bold.woff
panel_components/www/katex/fonts/KaTeX_Caligraphic-Regular.woff
panel_components/www/katex/fonts/KaTeX_Fraktur-Bold.woff
panel_components/www/katex/fonts/KaTeX_Fraktur-Regular.woff
panel_components/www/katex/fonts/KaTeX_Main-Bold.woff
panel_components/www/katex/fonts/KaTeX_Main-Italic.woff
panel_components/www/katex/fonts/KaTeX_Main-Regular.woff
panel_components/www/katex/fonts/KaTeX_Math-Italic.woff
panel_components/www/katex/fonts/KaTeX_SansSerif-Regular.woff
panel_components/www/katex/fonts/KaTeX_Script-Regular.woff
panel_components/www/katex/fonts/KaTeX_Size1-Regular.woff
panel_components/www/katex/fonts/KaTeX_Size2-Regular.woff
panel_components/www/katex/fonts/KaTeX_Size3-Regular.woff
panel_components/www/katex/fonts/KaTeX_Size4-Regular.woff
panel_components/www/katex/fonts/KaTeX_Typewriter-Regular.woff
panel_components/www/katex/fonts/uri_font.py
panel_components/www/katex/katex.css
panel_components/www/katex/katex.min.js
panel_components/www/mathjax/mathjax_tex-mml-am_chtml.js
panel_components/www/plotly/lodash.min.js
panel_components/www/plotly/plotly.min.js
panel_components/www/vega/vega-embed.js
panel_components/www/vega/vega-lite.js
panel_components/www/vega/vega.js
panel_components/www/vtk/vtk.js
panel_components/www/vue/vue.min.js
panel_components-0.1.2.dist-info/LICENSE
panel_components-0.1.2.dist-info/WHEEL
panel_components-0.1.2.dist-info/METADATA
panel_components-0.1.2.dist-info/RECORD
